{
 "admin" : {
  "id" : 1,
  "username" : "admin",
  "password" : "326af7a5f6481f0fa51345121aeda8e5",
  "is_admin" : true,
  "language" : "en_US",
  "is_disabled" : false,
  "directory" : "/var/lib/mldonkey/incoming/",
  "default_gui" : "Plex",
  "clients" : [ 1 ],
  "guis" : {
   "Plex" : {
    "css_style" : "default",
    "modules" : {
     "Titlebar" : { },
     "FileBrowser" : {
      "show_directories" : true,
      "show_hidden_files" : false,
      "allow_file_remove" : true
      },
     "Downloads" : {
      "columns" : [ "Check", "Networks", "Name", "ETA", "Percent", "Size", "Downloaded", "DownloadRate" ],
      "show_percent_bar" : true,
      "enable_row_colors" : true,
      "rotX" : 0
      },
     "Servers" : {
      "show_state" : "CONNECTED"
      },
     "Clients" : { },
     "Searches" : {
      "show_advanced" : false
      },
     "PageRefresh" : { },
     "UserSettings" : { },
     "ModuleSettings" : { },
     "ClientSettings" : { },
     "Links" : { },
     "Logout" : { }
     }
    },
   "Clutch" : { },
   "Jay" : { }
   }
  },
 "version" : "0.1.3"
 }
